pyconstant/__init__.py
pyconstant/main.py
pyconstant-1.0.0.dist-info/DESCRIPTION.rst
pyconstant-1.0.0.dist-info/METADATA
pyconstant-1.0.0.dist-info/RECORD
pyconstant-1.0.0.dist-info/WHEEL
pyconstant-1.0.0.dist-info/metadata.json
pyconstant-1.0.0.dist-info/top_level.txt
